jghfmanager/__init__.py
jghfmanager/cminferencer.py
jghfmanager/ensure_endpoint_paused.py
jghfmanager/jgthfcli.py
jghfmanager/jgthfdata.py
jghfmanager-0.1.9.dist-info/licenses/LICENSE
jghfmanager-0.1.9.dist-info/METADATA
jghfmanager-0.1.9.dist-info/WHEEL
jghfmanager-0.1.9.dist-info/entry_points.txt
jghfmanager-0.1.9.dist-info/top_level.txt
jghfmanager-0.1.9.dist-info/RECORD
