Metadata-Version: 2.4
Name: jghfmanager
Version: 0.1.9
Summary: A Python module jghfmanager
Home-page: https://github.com/jgwill/jghfmanager
Author: J.Guillaume D-Isabelle
License-File: LICENSE
Requires-Dist: tlid
Requires-Dist: requests
Requires-Dist: jgcmlib
Requires-Dist: huggingface_hub
Dynamic: author
Dynamic: home-page
Dynamic: license-file
Dynamic: requires-dist
Dynamic: summary
